VSautomatic/Auth_Token.txt
VSautomatic/DeviceDB.xml
VSautomatic/Dictionary.txt
VSautomatic/IR_Remote.xml
VSautomatic/MacroList.xml
VSautomatic/MyCamera.py
VSautomatic/MyRedRat.py
VSautomatic/MyTools.py
VSautomatic/NLog.config
VSautomatic/NLog.dll
VSautomatic/ReSTTerminal.py
VSautomatic/RedRat.dll
VSautomatic/RedRatHub.Connection.dll
VSautomatic/RedRatHub.py
VSautomatic/RedRatHubCmd.exe
VSautomatic/RedRatHubCmd.exe.config
VSautomatic/RedRatHubCore.dll
VSautomatic/RedRatHubS.py
VSautomatic/TestCfgParse.py
VSautomatic/Vizio.xml
VSautomatic/Vizio_IR.xml
VSautomatic/__init__.py
VSautomatic/deco.py
VSautomatic/my_serial.py
VSautomatic/restlog.txt
VSautomatic-2.7.dist-info/METADATA
VSautomatic-2.7.dist-info/WHEEL
VSautomatic-2.7.dist-info/top_level.txt
VSautomatic-2.7.dist-info/RECORD
